html_to_django/__init__.py
html_to_django/converter.py
html_to_django/formatters/__init__.py
html_to_django/formatters/assets_formatter.py
html_to_django/formatters/attr_formatter.py
html_to_django/formatters/block_formatter.py
html_to_django/formatters/command_formatter.py
html_to_django/formatters/for_formatter.py
html_to_django/formatters/for_wrap_formatter.py
html_to_django/formatters/if_formatter.py
html_to_django/formatters/include_formatter.py
html_to_django/formatters/remove_default_formatter.py
html_to_django/formatters/remove_formatter.py
html_to_django/formatters/static_formatter.py
html_to_django/formatters/style_formatter.py
html_to_django/formatters/style_raw_formatter.py
html_to_django/formatters/unwrap_formatter.py
html_to_django/formatters/var_formatter.py
html_to_django-0.0.2.dist-info/METADATA
html_to_django-0.0.2.dist-info/WHEEL
html_to_django-0.0.2.dist-info/entry_points.txt
html_to_django-0.0.2.dist-info/licenses/LICENSE.txt
html_to_django-0.0.2.dist-info/RECORD
