Metadata-Version: 2.3
Name: html_to_django
Version: 0.0.2
Summary: HTML to Django Converter
Project-URL: Homepage, https://github.com/truePhilipp/html_to_django
Project-URL: Issues, https://github.com/truePhilipp/html_to_django/issues
Author-email: Philipp Mayr <philipp@mayr.software>
License: MIT License
License-File: LICENSE.txt
Keywords: converter,django,html,static html,tool,web development
Classifier: License :: OSI Approved :: MIT License
Classifier: Operating System :: OS Independent
Classifier: Programming Language :: Python :: 3
Classifier: Programming Language :: Python :: 3.12
Requires-Python: >=3.12
Requires-Dist: beautifulsoup4==4.12.3
Provides-Extra: dev
Requires-Dist: hatch-vcs==0.4.0; extra == 'dev'
Requires-Dist: hatch==1.10.0; extra == 'dev'
Provides-Extra: test
Requires-Dist: mypy==1.9.0; extra == 'test'
Requires-Dist: pycodestyle==2.11.1; extra == 'test'
